pypi_multi_versions/__init__.py
pypi_multi_versions/cli.py
pypi_multi_versions/importer.py
pypi_multi_versions/installer.py
pypi_multi_versions-0.3.0.dist-info/LICENCE
pypi_multi_versions-0.3.0.dist-info/METADATA
pypi_multi_versions-0.3.0.dist-info/WHEEL
pypi_multi_versions-0.3.0.dist-info/entry_points.txt
pypi_multi_versions-0.3.0.dist-info/top_level.txt
pypi_multi_versions-0.3.0.dist-info/RECORD
