Metadata-Version: 2.1
Name: pypi-multi-versions
Version: 0.3.0
Summary: Manage multiple versions of PyPI packages
Home-page: https://github.com/frier-sam/pypi_multi_versions
Author: sam-iau
Author-email: shop2local@gmail.com
License: UNKNOWN
Platform: UNKNOWN
Classifier: Programming Language :: Python :: 3
Classifier: License :: OSI Approved :: MIT License
Classifier: Operating System :: OS Independent
Requires-Python: >=3.6
License-File: LICENCE
